vibe_testing/__init__.py
vibe_testing-0.0.3.dist-info/METADATA
vibe_testing-0.0.3.dist-info/WHEEL
vibe_testing-0.0.3.dist-info/licenses/LICENSE
vibe_testing-0.0.3.dist-info/RECORD
